Encoder/__init__.py
Encoder/encoder.py
Encoder-1.1.dist-info/LICENSE
Encoder-1.1.dist-info/METADATA
Encoder-1.1.dist-info/WHEEL
Encoder-1.1.dist-info/top_level.txt
Encoder-1.1.dist-info/RECORD
