Metadata-Version: 2.1
Name: Encoder
Version: 1.1
Summary: Encoder library for Raspberry Pi for measuring quadrature encoded signals.
Home-page: https://github.com/mivallion/Encoder
Author: Viktor Sevastyanov
Author-email: mivallion@example.com
License: UNKNOWN
Keywords: raspberrypi,encoder,gpio
Platform: UNKNOWN
Classifier: Programming Language :: Python :: 2
Classifier: Programming Language :: Python :: 2.7
Classifier: Programming Language :: Python :: 3
Classifier: Programming Language :: Python :: 3.2
Classifier: Programming Language :: Python :: 3.3
Classifier: Programming Language :: Python :: 3.4
Classifier: Programming Language :: Python :: 3.5
Classifier: Programming Language :: Python :: 3.6
Classifier: Programming Language :: Python :: 3.7
Classifier: License :: OSI Approved :: MIT License
Classifier: Operating System :: POSIX :: Linux
